{
 "activate_count_icon": 0,
 "charts": [
  {
   "chart_name": "Request Report",
   "label": "Request Report"
  }
 ],
 "content": "[{\"id\":\"ec1F-jIO5A\",\"type\":\"header\",\"data\":{\"text\":\"<span class=\\\"h4\\\">Smart FM</span>\",\"col\":12}},{\"id\":\"dhi2td2O7b\",\"type\":\"chart\",\"data\":{\"chart_name\":\"Request Report\",\"col\":12}},{\"id\":\"KwQzTV_xhR\",\"type\":\"header\",\"data\":{\"text\":\"<span class=\\\"h4\\\"><b>Your Shortcuts</b></span>\",\"col\":12}},{\"id\":\"kRElbJGgi-\",\"type\":\"shortcut\",\"data\":{\"shortcut_name\":\"Maintenance Request\",\"col\":3}},{\"id\":\"T_ELHHUDFO\",\"type\":\"shortcut\",\"data\":{\"shortcut_name\":\"Incident Report\",\"col\":3}},{\"id\":\"AgmTrpMCu0\",\"type\":\"shortcut\",\"data\":{\"shortcut_name\":\"Access Request\",\"col\":3}},{\"id\":\"sQwP2Ln4-Z\",\"type\":\"shortcut\",\"data\":{\"shortcut_name\":\"Inspection Checklist\",\"col\":3}},{\"id\":\"RWvULbK__5\",\"type\":\"header\",\"data\":{\"text\":\"<span class=\\\"h4\\\"><b>Calendar</b></span>\",\"col\":12}},{\"id\":\"PJHWO3mD8P\",\"type\":\"shortcut\",\"data\":{\"shortcut_name\":\"ToDo Calendar\",\"col\":3}},{\"id\":\"Ca02m-kfPg\",\"type\":\"spacer\",\"data\":{\"col\":12}},{\"id\":\"zvBL_ORvId\",\"type\":\"header\",\"data\":{\"text\":\"<span class=\\\"h4\\\"><b>Reports and Masters</b></span>\",\"col\":12}},{\"id\":\"aZ_aYZfJAK\",\"type\":\"card\",\"data\":{\"card_name\":\"Requests\",\"col\":4}},{\"id\":\"ZZ9XJ0Eg0e\",\"type\":\"card\",\"data\":{\"card_name\":\"Form\",\"col\":4}},{\"id\":\"KJP0ulpGyr\",\"type\":\"card\",\"data\":{\"card_name\":\"Reports\",\"col\":4}}]",
 "creation": "2023-05-17 14:02:00.454211",
 "docstatus": 0,
 "doctype": "Workspace",
 "for_user": "",
 "hide_custom": 0,
 "icon": "file",
 "idx": 0,
 "is_hidden": 0,
 "label": "Smart FM",
 "links": [
  {
   "hidden": 0,
   "is_query_report": 0,
   "label": "Requests",
   "link_count": 3,
   "link_type": "DocType",
   "onboard": 0,
   "type": "Card Break"
  },
  {
   "hidden": 0,
   "is_query_report": 0,
   "label": "Maintenance Request",
   "link_count": 0,
   "link_to": "Maintenance Request",
   "link_type": "DocType",
   "onboard": 0,
   "type": "Link"
  },
  {
   "hidden": 0,
   "is_query_report": 0,
   "label": "Access Request",
   "link_count": 0,
   "link_to": "Access Request",
   "link_type": "DocType",
   "onboard": 0,
   "type": "Link"
  },
  {
   "hidden": 0,
   "is_query_report": 0,
   "label": "Key Control",
   "link_count": 0,
   "link_to": "Key Control",
   "link_type": "DocType",
   "onboard": 0,
   "type": "Link"
  },
  {
   "hidden": 0,
   "is_query_report": 0,
   "label": "Reports",
   "link_count": 1,
   "link_type": "DocType",
   "onboard": 0,
   "type": "Card Break"
  },
  {
   "hidden": 0,
   "is_query_report": 0,
   "label": "Incident Report",
   "link_count": 0,
   "link_to": "Incident Report",
   "link_type": "DocType",
   "onboard": 0,
   "type": "Link"
  },
  {
   "hidden": 0,
   "is_query_report": 0,
   "label": "Form",
   "link_count": 5,
   "onboard": 0,
   "type": "Card Break"
  },
  {
   "hidden": 0,
   "is_query_report": 0,
   "label": "Emergency Contact Information",
   "link_count": 0,
   "link_to": "Emergency Contact Information",
   "link_type": "DocType",
   "onboard": 0,
   "type": "Link"
  },
  {
   "hidden": 0,
   "is_query_report": 0,
   "label": "Vendor Registration",
   "link_count": 0,
   "link_to": "Vendor Registration",
   "link_type": "DocType",
   "onboard": 0,
   "type": "Link"
  },
  {
   "hidden": 0,
   "is_query_report": 0,
   "label": "Inspection Checklist",
   "link_count": 0,
   "link_to": "Inspection Checklist",
   "link_type": "DocType",
   "onboard": 0,
   "type": "Link"
  },
  {
   "hidden": 0,
   "is_query_report": 0,
   "label": "Tenant Feedback",
   "link_count": 0,
   "link_to": "Tenant Feedback",
   "link_type": "DocType",
   "onboard": 0,
   "type": "Link"
  },
  {
   "hidden": 0,
   "is_query_report": 0,
   "label": "Building Environment Feedback",
   "link_count": 0,
   "link_to": "Building Environment Feedback",
   "link_type": "DocType",
   "onboard": 0,
   "type": "Link"
  }
 ],
 "modified": "2023-11-01 10:42:35.168406",
 "modified_by": "Administrator",
 "module": "Smart FM",
 "name": "Smart FM",
 "number_cards": [],
 "owner": "Administrator",
 "parent_page": "",
 "public": 1,
 "quick_lists": [],
 "roles": [],
 "sequence_id": 2.0,
 "shortcuts": [
  {
   "color": "Yellow",
   "doc_view": "List",
   "format": "{} Issued",
   "label": "Maintenance Request",
   "link_to": "Maintenance Request",
   "stats_filter": "{\"workflow_state\":[\"=\",\"Issued\"]}",
   "type": "DocType"
  },
  {
   "color": "Red",
   "doc_view": "List",
   "format": "{} Issued",
   "label": "Incident Report",
   "link_to": "Incident Report",
   "stats_filter": "{\"workflow_state\":[\"=\",\"Issued\"]}",
   "type": "DocType"
  },
  {
   "color": "Yellow",
   "doc_view": "List",
   "format": "{} Issued",
   "label": "Access Request",
   "link_to": "Access Request",
   "stats_filter": "{\"workflow_state\":[\"=\",\"Issued\"]}",
   "type": "DocType"
  },
  {
   "color": "Grey",
   "doc_view": "List",
   "label": "ToDo Calendar",
   "type": "URL",
   "url": "https://smart-fm-dev.arber.ai/app/todo/view/calendar/default"
  },
  {
   "color": "Cyan",
   "doc_view": "List",
   "format": "{} Issued",
   "label": "Inspection Checklist",
   "link_to": "Inspection Checklist",
   "stats_filter": "{\"workflow_state\":[\"=\",null]}",
   "type": "DocType"
  }
 ],
 "title": "Smart FM"
}